myhdl/_Cosimulation.py
myhdl/_ShadowSignal.py
myhdl/_Signal.py
myhdl/_Simulation.py
myhdl/_Waiter.py
myhdl/__init__.py
myhdl/_always.py
myhdl/_always_comb.py
myhdl/_always_seq.py
myhdl/_bin.py
myhdl/_block.py
myhdl/_concat.py
myhdl/_delay.py
myhdl/_enum.py
myhdl/_extractHierarchy.py
myhdl/_getHierarchy.py
myhdl/_getcellvars.py
myhdl/_hdlclass.py
myhdl/_instance.py
myhdl/_intbv.py
myhdl/_join.py
myhdl/_misc.py
myhdl/_modbv.py
myhdl/_openport.py
myhdl/_resolverefs.py
myhdl/_simulator.py
myhdl/_traceSignals.py
myhdl/_tristate.py
myhdl/_util.py
myhdl/_visitors.py
myhdl/debug.py
myhdl/conversion/_VHDLNameValidation.py
myhdl/conversion/__init__.py
myhdl/conversion/_analyze.py
myhdl/conversion/_misc.py
myhdl/conversion/_toVHDL.py
myhdl/conversion/_toVHDLPackage.py
myhdl/conversion/_toVerilog.py
myhdl/conversion/_verify.py
myhdl-0.11.51.data/data/share/myhdl/cosimulation/cver/Makefile.lnx
myhdl-0.11.51.data/data/share/myhdl/cosimulation/cver/Makefile.lnx64
myhdl-0.11.51.data/data/share/myhdl/cosimulation/cver/Makefile.osx
myhdl-0.11.51.data/data/share/myhdl/cosimulation/cver/README.txt
myhdl-0.11.51.data/data/share/myhdl/cosimulation/cver/myhdl_vpi.c
myhdl-0.11.51.data/data/share/myhdl/cosimulation/cver/test/bin2gray.py
myhdl-0.11.51.data/data/share/myhdl/cosimulation/cver/test/dff.py
myhdl-0.11.51.data/data/share/myhdl/cosimulation/cver/test/dff_clkout.py
myhdl-0.11.51.data/data/share/myhdl/cosimulation/cver/test/inc.py
myhdl-0.11.51.data/data/share/myhdl/cosimulation/cver/test/test_all.py
myhdl-0.11.51.data/data/share/myhdl/cosimulation/icarus/Makefile
myhdl-0.11.51.data/data/share/myhdl/cosimulation/icarus/README.txt
myhdl-0.11.51.data/data/share/myhdl/cosimulation/icarus/myhdl.c
myhdl-0.11.51.data/data/share/myhdl/cosimulation/icarus/myhdl_20030518.c
myhdl-0.11.51.data/data/share/myhdl/cosimulation/icarus/myhdl_table.c
myhdl-0.11.51.data/data/share/myhdl/cosimulation/icarus/test/bin2gray.py
myhdl-0.11.51.data/data/share/myhdl/cosimulation/icarus/test/const_1.py
myhdl-0.11.51.dist-info/LICENSE.txt
myhdl-0.11.51.dist-info/METADATA
myhdl-0.11.51.dist-info/WHEEL
myhdl-0.11.51.dist-info/top_level.txt
myhdl-0.11.51.dist-info/RECORD
